m360/__init__.py
m360/ptelegraf.py
m360/agents/__init__.py
m360/agents/apache/__init__.py
m360/agents/apache/instance.py
m360/agents/apache/manager.py
m360/agents/apache/monitor.py
m360/agents/apache/settings.py
m360/agents/custom/__init__.py
m360/agents/custom/instance.py
m360/agents/custom/monitor.py
m360/agents/custom/settings.py
m360/agents/internal/__init__.py
m360/agents/internal/instance.py
m360/agents/internal/monitor.py
m360/agents/internal/settings.py
m360/agents/jboss/__init__.py
m360/agents/jboss/instance.py
m360/agents/jboss/manager.py
m360/agents/jboss/monitor.py
m360/agents/jboss/settings.py
m360/agents/jboss/jmxmonitor/JBossJMXClient4.jar
m360/agents/jboss/jmxmonitor/JBossJMXClient5.jar
m360/agents/jboss/jmxmonitor/JBossJMXClient6_jre6.jar
m360/agents/jboss/jmxmonitor/JBossJMXClient6_jre7.jar
m360/agents/jboss/jmxmonitor/__init__.py
m360/agents/oracle/__init__.py
m360/agents/oracle/instance.py
m360/agents/oracle/manager.py
m360/agents/oracle/monitor.py
m360/agents/oracle/settings.py
m360/agents/oraclecloud/__init__.py
m360/agents/oraclecloud/instance.py
m360/agents/oraclecloud/manager.py
m360/agents/oraclecloud/monitor.py
m360/agents/oraclecloud/settings.py
m360/agents/procstat/__init__.py
m360/agents/procstat/instance.py
m360/agents/procstat/monitor.py
m360/agents/procstat/settings.py
m360/agents/tomcat/__init__.py
m360/agents/tomcat/instance.py
m360/agents/tomcat/manager.py
m360/agents/tomcat/monitor.py
m360/agents/tomcat/settings.py
m360/agents/unix/__init__.py
m360/agents/unix/instance.py
m360/agents/unix/manager.py
m360/agents/unix/monitor.py
m360/agents/unix/settings.py
m360/agents/weblogic/__init__.py
m360/agents/weblogic/instance.py
m360/agents/weblogic/manager.py
m360/agents/weblogic/monitor.py
m360/agents/weblogic/settings.py
m360/agents/weblogic/jmxmonitor/__init__.py
m360/agents/weblogic/jmxmonitor/weblogicmonitor11g_JRE17.jar
m360/agents/weblogic/lib/__init__.py
m360/agents/weblogic/lib/wls.py
m360/agents/weblogic/lib/wlsrestful11g.py
m360_ptelegraf-3.2.2.dist-info/LICENSE
m360_ptelegraf-3.2.2.dist-info/METADATA
m360_ptelegraf-3.2.2.dist-info/WHEEL
m360_ptelegraf-3.2.2.dist-info/entry_points.txt
m360_ptelegraf-3.2.2.dist-info/top_level.txt
m360_ptelegraf-3.2.2.dist-info/zip-safe
m360_ptelegraf-3.2.2.dist-info/RECORD
